{
 "fmuExporter": [
  {
   "is_class": false,
   "is_explicit": false,
   "module": "otfmi.function_exporter",
   "module_short": "otfmi",
   "name": "FunctionExporter"
  },
  {
   "is_class": false,
   "is_explicit": false,
   "module": "otfmi",
   "module_short": "otfmi",
   "name": "FunctionExporter"
  }
 ],
 "fmuExporter.export_fmu": [
  {
   "is_class": false,
   "is_explicit": false,
   "module": "otfmi.function_exporter",
   "module_short": "otfmi",
   "name": "FunctionExporter.export_fmu"
  },
  {
   "is_class": false,
   "is_explicit": false,
   "module": "otfmi",
   "module_short": "otfmi",
   "name": "FunctionExporter.export_fmu"
  }
 ],
 "fmu_path": [
  {
   "is_class": false,
   "is_explicit": false,
   "module": "builtins",
   "module_short": "builtins",
   "name": "str"
  }
 ],
 "func": [
  {
   "is_class": false,
   "is_explicit": false,
   "module": "openturns.func",
   "module_short": "openturns",
   "name": "SymbolicFunction"
  },
  {
   "is_class": false,
   "is_explicit": false,
   "module": "openturns",
   "module_short": "openturns",
   "name": "SymbolicFunction"
  }
 ],
 "inputPoint": [
  {
   "is_class": false,
   "is_explicit": false,
   "module": "builtins",
   "module_short": "builtins",
   "name": "list"
  }
 ],
 "join": [
  {
   "is_class": false,
   "is_explicit": false,
   "module": "builtins",
   "module_short": "builtins",
   "name": "function"
  },
  {
   "is_class": false,
   "is_explicit": false,
   "module": "os.path",
   "module_short": "os.path",
   "name": "join"
  }
 ],
 "ot.SymbolicFunction": [
  {
   "is_class": true,
   "is_explicit": false,
   "module": "openturns.func",
   "module_short": "openturns",
   "name": "SymbolicFunction"
  },
  {
   "is_class": true,
   "is_explicit": false,
   "module": "openturns",
   "module_short": "openturns",
   "name": "SymbolicFunction"
  },
  {
   "is_class": true,
   "is_explicit": false,
   "module": "openturns.func",
   "module_short": "openturns",
   "name": "Function"
  },
  {
   "is_class": true,
   "is_explicit": false,
   "module": "openturns",
   "module_short": "openturns",
   "name": "Function"
  },
  {
   "is_class": true,
   "is_explicit": false,
   "module": "openturns.func",
   "module_short": "openturns.func",
   "name": "_FunctionImplementationTypedInterfaceObject"
  },
  {
   "is_class": true,
   "is_explicit": false,
   "module": "openturns",
   "module_short": "openturns",
   "name": "_FunctionImplementationTypedInterfaceObject"
  },
  {
   "is_class": true,
   "is_explicit": false,
   "module": "openturns.common",
   "module_short": "openturns",
   "name": "InterfaceObject"
  },
  {
   "is_class": true,
   "is_explicit": false,
   "module": "openturns",
   "module_short": "openturns",
   "name": "InterfaceObject"
  },
  {
   "is_class": true,
   "is_explicit": false,
   "module": "openturns.common",
   "module_short": "openturns",
   "name": "Object"
  },
  {
   "is_class": true,
   "is_explicit": false,
   "module": "openturns",
   "module_short": "openturns",
   "name": "Object"
  },
  {
   "is_class": false,
   "is_explicit": false,
   "module": "openturns",
   "module_short": "openturns",
   "name": "SymbolicFunction"
  }
 ],
 "otfmi.FunctionExporter": [
  {
   "is_class": true,
   "is_explicit": false,
   "module": "otfmi.function_exporter",
   "module_short": "otfmi",
   "name": "FunctionExporter"
  },
  {
   "is_class": true,
   "is_explicit": false,
   "module": "otfmi",
   "module_short": "otfmi",
   "name": "FunctionExporter"
  },
  {
   "is_class": false,
   "is_explicit": false,
   "module": "otfmi",
   "module_short": "otfmi",
   "name": "FunctionExporter"
  }
 ],
 "tempfile.mkdtemp": [
  {
   "is_class": false,
   "is_explicit": false,
   "module": "builtins",
   "module_short": "builtins",
   "name": "function"
  },
  {
   "is_class": false,
   "is_explicit": false,
   "module": "tempfile",
   "module_short": "tempfile",
   "name": "mkdtemp"
  }
 ]
}